sprl/__init__.py
sprl/parser.py
sprl_parser/__init__.py
sprl_parser/parser.py
tests/__init__.py
tests/test_parser.py
sprl-0.0.2.dist-info/LICENSE
sprl-0.0.2.dist-info/METADATA
sprl-0.0.2.dist-info/WHEEL
sprl-0.0.2.dist-info/top_level.txt
sprl-0.0.2.dist-info/RECORD
